badsecrets/__init__.py
badsecrets/base.py
badsecrets/errors.py
badsecrets/examples/__init__.py
badsecrets/examples/blacklist3r.py
badsecrets/examples/cli.py
badsecrets/examples/symfony_knownkey.py
badsecrets/examples/telerik_knownkey.py
badsecrets/helpers.py
badsecrets/modules/__init__.py
badsecrets/modules/aspnet_compressedviewstate.py
badsecrets/modules/aspnet_viewstate.py
badsecrets/modules/django_signedcookies.py
badsecrets/modules/express_signedcookies_cs.py
badsecrets/modules/express_signedcookies_es.py
badsecrets/modules/flask_signedcookies.py
badsecrets/modules/generic_jwt.py
badsecrets/modules/jsf_viewstate.py
badsecrets/modules/laravel_signedcookies.py
badsecrets/modules/peoplesoft_pstoken.py
badsecrets/modules/rack2_signedcookies.py
badsecrets/modules/rails_secretkeybase.py
badsecrets/modules/symfony_signedurl.py
badsecrets/modules/telerik_encryptionkey.py
badsecrets/modules/telerik_hashkey.py
badsecrets/modules/yii2_signedcookies.py
badsecrets/resources/aspnet_machinekeys.txt
badsecrets/resources/django_secret_keys.txt
badsecrets/resources/express_session_secrets.txt
badsecrets/resources/flask_secret_keys.txt
badsecrets/resources/jsf_viewstate_passwords.txt
badsecrets/resources/jsf_viewstate_passwords_b64.txt
badsecrets/resources/jwt_rsakeys_private.txt
badsecrets/resources/jwt_rsakeys_public.txt
badsecrets/resources/jwt_secrets.txt
badsecrets/resources/laravel_app_keys.txt
badsecrets/resources/peoplesoft_passwords.txt
badsecrets/resources/rack_secret_keys.txt
badsecrets/resources/rails_secret_key_base.txt
badsecrets/resources/symfony_appsecret.txt
badsecrets/resources/telerik_encryption_keys.txt
badsecrets/resources/telerik_hash_keys.txt
badsecrets/resources/top_100000_passwords.txt
badsecrets/resources/yii2_cookieValidationKeys.txt
badsecrets-0.13.47.dist-info/METADATA
badsecrets-0.13.47.dist-info/WHEEL
badsecrets-0.13.47.dist-info/entry_points.txt
badsecrets-0.13.47.dist-info/licenses/LICENSE
badsecrets-0.13.47.dist-info/RECORD
